Metadata-Version: 2.1
Name: JellySport
Version: 1.0.7
Summary: Scrapes popular streaming sites and compiles m3u/xml files for viewing.
Home-page: http://pypi.python.org/pypi/sportyfin/
Author: Axel Mierczuk
Author-email: axelmierczuk@gmail.com
License: LICENSE.txt
Platform: any
Classifier: Development Status :: 4 - Beta
Classifier: Intended Audience :: Telecommunications Industry
Classifier: License :: OSI Approved :: MIT License
Classifier: Programming Language :: Python
Classifier: Programming Language :: Python :: 3
Classifier: Programming Language :: Python :: 3.4
Classifier: Programming Language :: Python :: 3.5
Classifier: Programming Language :: Python :: 3.9
